{
  "Name": "Custom_Model",
  "Transform": {
    "posX": -11.4442053,
    "posY": -3.87426853,
    "posZ": -1.84168613,
    "rotX": -0.000214563988,
    "rotY": 135.025467,
    "rotZ": 358.491943,
    "scaleX": 2.199999,
    "scaleY": 2.199999,
    "scaleZ": 2.199999
  },
  "Nickname": "TIE Fighter [Heavy Cover]",
  "ColorDiffuse": {
    "r": 0.541207552,
    "g": 0.6190865,
    "b": 0.676471
  },
  "Locked": true,
  "Grid": true,
  "Snap": true,
  "IgnoreFoW": false,
  "Autoraise": true,
  "Sticky": true,
  "Tooltip": true,
  "GridProjection": false,
  "HideWhenFaceDown": false,
  "Hands": false,
  "CustomMesh": {
    "MeshURL": "http://cloud-3.steamusercontent.com/ugc/787482161151594281/0C8E0874A67198A45EE8AF0BE9E0329ABB8A8859/",
    "DiffuseURL": "http://cloud-3.steamusercontent.com/ugc/787482161151594462/4C6AB300622163D7861584FE38E350EF6B844766/",
    "NormalURL": "",
    "ColliderURL": "http://cloud-3.steamusercontent.com/ugc/787482161151594281/0C8E0874A67198A45EE8AF0BE9E0329ABB8A8859/",
    "Convex": true,
    "MaterialIndex": 3,
    "TypeIndex": 1,
    "CastShadows": true
  },
  "GUID": "e262db"
}
