{
  "Name": "Custom_Model",
  "Transform": {
    "posX": 11.5586538,
    "posY": 2.43229532,
    "posZ": 5.381569,
    "rotX": -0.000792251958,
    "rotY": 210.118622,
    "rotZ": -0.000702974445,
    "scaleX": 1,
    "scaleY": 1,
    "scaleZ": 1
  },
  "Nickname": "Building [Heavy Cover]",
  "ColorDiffuse": {
    "r": 0.775261343,
    "g": 0.730690658,
    "b": 0.700976849
  },
  "Locked": true,
  "Grid": true,
  "Snap": true,
  "IgnoreFoW": false,
  "Autoraise": true,
  "Sticky": true,
  "Tooltip": true,
  "GridProjection": false,
  "HideWhenFaceDown": false,
  "Hands": false,
  "CustomMesh": {
    "MeshURL": "http://cloud-3.steamusercontent.com/ugc/966480765117280301/5F0F43310339CDAF404670B5ECEB85D11FC144B6/",
    "DiffuseURL": "http://cloud-3.steamusercontent.com/ugc/966480765117280490/8447EB7988EAC8A49026483D1A827F583CDD65C3/",
    "NormalURL": "",
    "ColliderURL": "http://cloud-3.steamusercontent.com/ugc/966480765118137348/D72837CFC7753DF14B9947295DD1E8BF2E64C6D5/",
    "Convex": false,
    "MaterialIndex": 3,
    "TypeIndex": 0,
    "CastShadows": true
  },
  "GUID": "9da80c"
}
