{
  "Name": "Custom_Model",
  "Transform": {
    "posX": -8.940245,
    "posY": 1.44551611,
    "posZ": -2.77561331,
    "rotX": -0.00117897452,
    "rotY": 44.9927139,
    "rotZ": -0.00118951662,
    "scaleX": 0.850000143,
    "scaleY": 0.850000143,
    "scaleZ": 0.850000143
  },
  "Nickname": "Walkway [Light Cover]",
  "ColorDiffuse": {
    "r": 1,
    "g": 1,
    "b": 1
  },
  "Locked": true,
  "Grid": true,
  "Snap": true,
  "IgnoreFoW": false,
  "Autoraise": true,
  "Sticky": true,
  "Tooltip": true,
  "GridProjection": false,
  "Hands": false,
  "CustomMesh": {
    "MeshURL": "http://cloud-3.steamusercontent.com/ugc/785234780857934075/67F7C0F3E85631B8F905462331257564ADE7F101/",
    "DiffuseURL": "http://cloud-3.steamusercontent.com/ugc/785234780857945775/3005C4F30CA2D9ADBBD18789023A30888FDA4DA5/",
    "NormalURL": "",
    "ColliderURL": "http://cloud-3.steamusercontent.com/ugc/924802058713318404/E46A0DB14CBAD8B6711484041D221EC8DFE6498A/",
    "Convex": true,
    "MaterialIndex": 3,
    "TypeIndex": 0,
    "CastShadows": true
  },
  "GUID": "03968b"
}
