{
  "Name": "Custom_Assetbundle",
  "Transform": {
    "posX": 20.8974419,
    "posY": 2.340743,
    "posZ": -6.02940845,
    "rotX": -0.00168944127,
    "rotY": 0.00472305,
    "rotZ": -0.00001976592,
    "scaleX": 1,
    "scaleY": 1,
    "scaleZ": 1
  },
  "Nickname": "Doorway",
  "ColorDiffuse": {
    "r": 1,
    "g": 1,
    "b": 1
  },
  "Locked": true,
  "Grid": true,
  "Snap": true,
  "IgnoreFoW": false,
  "Autoraise": true,
  "Sticky": true,
  "Tooltip": true,
  "GridProjection": false,
  "HideWhenFaceDown": false,
  "Hands": false,
  "CustomAssetbundle": {
    "AssetbundleURL": "http://cloud-3.steamusercontent.com/ugc/851592766469588710/179F71024E53EA6D717D41D62C5AF0E76A8D932C/",
    "AssetbundleSecondaryURL": "",
    "MaterialIndex": 2,
    "TypeIndex": 1,
    "LoopingEffectIndex": 0
  },
  "GUID": "e56e76"
}
