{
  "Object": {
    "GUID": "ca106f",
    "Name": "Custom_Model",
    "Transform": {
      "posX": 43.6538773,
      "posY": 1.0502187,
      "posZ": 18.8204632,
      "rotX": 0,
      "rotY": 0,
      "rotZ": 0,
      "scaleX": 1,
      "scaleY": 1,
      "scaleZ": 1
    },
    "Nickname": "Condition Token",
    "Description": "",
    "GMNotes": "",
    "ColorDiffuse": {
      "r": 1,
      "g": 1,
      "b": 1
    },
    "LayoutGroupSortIndex": 0,
    "Locked": false,
    "Grid": true,
    "Snap": true,
    "IgnoreFoW": false,
    "MeasureMovement": false,
    "DragSelectable": true,
    "Autoraise": true,
    "Sticky": true,
    "Tooltip": true,
    "GridProjection": false,
    "HideWhenFaceDown": false,
    "Hands": false,
    "CustomMesh": {
      "MeshURL": "http://cloud-3.steamusercontent.com/ugc/786359883314441337/A0DD41660FEC7E450F2EDF38191AF3C26E826C49/",
      "DiffuseURL": "http://cloud-3.steamusercontent.com/ugc/786359883314441794/A5214853EF5CF66714FC230767A634761777F6A9/",
      "NormalURL": "",
      "ColliderURL": "",
      "Convex": true,
      "MaterialIndex": 3,
      "TypeIndex": 0,
      "CastShadows": true
    },
    "LuaScript": "#include ./Condition_Token.ca106f.lua",
    "LuaScriptState": "",
    "XmlUI": ""
  },
  "StatesPaths": {}
}
