{
  "Name": "Custom_Model",
  "Transform": {
    "posX": 36.6843529,
    "posY": 3.08835983,
    "posZ": 0.847342432,
    "rotX": 0.008690784,
    "rotY": 89.97991,
    "rotZ": 359.988037,
    "scaleX": 0.8000002,
    "scaleY": 0.9660997,
    "scaleZ": 0.8000002
  },
  "Nickname": "Rock Formation [Heavy Cover]",
  "ColorDiffuse": {
    "r": 0.9999998,
    "g": 0.992160857,
    "b": 0.9999998
  },
  "Locked": true,
  "Grid": false,
  "Snap": false,
  "IgnoreFoW": false,
  "Autoraise": false,
  "Sticky": false,
  "Tooltip": true,
  "GridProjection": false,
  "HideWhenFaceDown": false,
  "Hands": false,
  "CustomMesh": {
    "MeshURL": "http://cloud-3.steamusercontent.com/ugc/785234780858991717/7752B8B026E0C06D7EF50CD4BBE62C151EAFB077/",
    "DiffuseURL": "http://cloud-3.steamusercontent.com/ugc/785234780858991957/09F6813045E368746D643B0CA3897B2011478EB0/",
    "NormalURL": "",
    "ColliderURL": "http://cloud-3.steamusercontent.com/ugc/785234780858991717/7752B8B026E0C06D7EF50CD4BBE62C151EAFB077/",
    "Convex": false,
    "MaterialIndex": 3,
    "TypeIndex": 0,
    "CastShadows": true
  },
  "GUID": "6ad6b1"
}
