{
  "Object": {
    "GUID": "c282f8",
    "Name": "Notecard",
    "Transform": {
      "posX": 6.61458635,
      "posY": 1.0190376,
      "posZ": 3.57237124,
      "rotX": 0.000007968873,
      "rotY": 0.00000256699013,
      "rotZ": -0.00000124903056,
      "scaleX": 1,
      "scaleY": 1,
      "scaleZ": 1
    },
    "Nickname": "3.1.0 - Beta",
    "Description": "Added Featured > Skirmish maps. See https://go.swlegion.dev/skirmish for details.\n\nFixed a bug where in the latest version of TTS miniatures no longer spawned from the list builders.\n\nFixed a bug where a unit deactivated when it was moved or picked up.",
    "GMNotes": "",
    "ColorDiffuse": {
      "r": 1,
      "g": 1,
      "b": 1
    },
    "LayoutGroupSortIndex": 0,
    "Locked": false,
    "Grid": true,
    "Snap": true,
    "IgnoreFoW": false,
    "MeasureMovement": false,
    "DragSelectable": true,
    "Autoraise": true,
    "Sticky": true,
    "Tooltip": true,
    "GridProjection": false,
    "HideWhenFaceDown": false,
    "Hands": false,
    "LuaScript": "",
    "LuaScriptState": "",
    "XmlUI": ""
  },
  "StatesPaths": {}
}
