{
  "Object": {
    "GUID": "526772",
    "Name": "Custom_Model",
    "Transform": {
      "posX": 8.000114,
      "posY": 0.941499,
      "posZ": -0.0000280538261,
      "rotX": -0.00160514389,
      "rotY": 0.000277464336,
      "rotZ": -2.24411352e-8,
      "scaleX": 1,
      "scaleY": 1,
      "scaleZ": 1
    },
    "Nickname": "BATTLEFIELD",
    "Description": "",
    "GMNotes": "",
    "ColorDiffuse": {
      "r": 0.932913363,
      "g": 0.932913363,
      "b": 0.932913363
    },
    "LayoutGroupSortIndex": 0,
    "Locked": true,
    "Grid": true,
    "Snap": true,
    "IgnoreFoW": false,
    "MeasureMovement": false,
    "DragSelectable": true,
    "Autoraise": true,
    "Sticky": true,
    "Tooltip": true,
    "GridProjection": true,
    "Hands": false,
    "CustomMesh": {
      "MeshURL": "http://cloud-3.steamusercontent.com/ugc/785234780859015647/B98B08E01F9F286630AE190B71A63A3BDD6F3E42/",
      "DiffuseURL": "http://cloud-3.steamusercontent.com/ugc/785234780866455500/634A609BB41112AE4C585F20ECA4EBB85AA6DEE6/",
      "NormalURL": "",
      "ColliderURL": "http://cloud-3.steamusercontent.com/ugc/785234780859051709/31241B5FBBF2E5081071E21AD980B4183E41FD02/",
      "Convex": true,
      "MaterialIndex": 3,
      "TypeIndex": 0,
      "CastShadows": true
    },
    "LuaScript": "#include ./BATTLEFIELD.526772.lua",
    "LuaScriptState": "",
    "XmlUI": ""
  },
  "StatesPaths": {}
}
