{
  "Name": "Custom_Model",
  "Transform": {
    "posX": 8.014018,
    "posY": 2.34470916,
    "posZ": 10.6070013,
    "rotX": 0.00266225543,
    "rotY": 179.990448,
    "rotZ": 0.000630295661,
    "scaleX": 0.375,
    "scaleY": 0.375,
    "scaleZ": 0.375
  },
  "Nickname": "",
  "ColorDiffuse": {
    "r": 1,
    "g": 0.333332449,
    "b": 0
  },
  "Locked": true,
  "Grid": true,
  "Snap": true,
  "IgnoreFoW": false,
  "Autoraise": true,
  "Sticky": true,
  "Tooltip": true,
  "GridProjection": false,
  "HideWhenFaceDown": false,
  "Hands": false,
  "CustomMesh": {
    "MeshURL": "http://cloud-3.steamusercontent.com/ugc/993512944591402965/6811510D8894A05E27588B12A9B7EA412F6B4E19/",
    "DiffuseURL": "http://cloud-3.steamusercontent.com/ugc/993512944591403079/C724CBB9E59301F928725F9003EC078648E78E1F/",
    "NormalURL": "",
    "ColliderURL": "http://cloud-3.steamusercontent.com/ugc/993512944591403281/622A25600F3E8048060DEC24FEF97169185CA517/",
    "Convex": false,
    "MaterialIndex": 1,
    "TypeIndex": 0,
    "CustomShader": {
      "SpecularColor": {
        "r": 0.8745098,
        "g": 0.8117647,
        "b": 0.745098054
      },
      "SpecularIntensity": 0,
      "SpecularSharpness": 3,
      "FresnelStrength": 0.1
    },
    "CastShadows": true
  },
  "GUID": "bb2fd2"
}
