{
  "Name": "Custom_Assetbundle",
  "Transform": {
    "posX": 12.9923944,
    "posY": 1.2331661,
    "posZ": -8.995992,
    "rotX": 359.9869,
    "rotY": 359.318756,
    "rotZ": 0.009938119,
    "scaleX": 1,
    "scaleY": 1,
    "scaleZ": 1
  },
  "Nickname": "",
  "ColorDiffuse": {
    "r": 0.141162962,
    "g": 0.141162962,
    "b": 0.141162962
  },
  "Locked": true,
  "Grid": true,
  "Snap": true,
  "IgnoreFoW": false,
  "Autoraise": true,
  "Sticky": true,
  "Tooltip": true,
  "GridProjection": false,
  "HideWhenFaceDown": false,
  "Hands": false,
  "CustomAssetbundle": {
    "AssetbundleURL": "http://cloud-3.steamusercontent.com/ugc/851592766469460618/BFA68BDB854352FD4D8D4E504FE5D6521555A882/",
    "AssetbundleSecondaryURL": "",
    "MaterialIndex": 3,
    "TypeIndex": 0,
    "LoopingEffectIndex": 0
  },
  "GUID": "b5e585"
}
